{
  "sourceId": "philosophie-magazine",
  "sourceName": "Philosophie Magazine",
  "fetchedAt": "2026-04-22T01:59:20.444110+00:00",
  "items": [
    {
      "title": "Les Iraniens font-ils la guerre comme les Perses de l’Antiquité ?",
      "url": "https://www.philomag.com/articles/les-iraniens-font-ils-la-guerre-comme-les-perses-de-lantiquite",
      "description": "",
      "date": "Tue, 21 Apr 2026",
      "thumbnail": "",
      "videoId": "",
      "priority": 5,
      "scoreDetail": {
        "daily": 5,
        "phil": 0,
        "flaneur": 0,
        "novelty": 0,
        "total": 5
      }
    },
    {
      "title": "La chanteuse Peaches répond à notre “Questionnaire de Socrate”",
      "url": "https://www.philomag.com/articles/la-chanteuse-peaches-repond-notre-questionnaire-de-socrate",
      "description": "",
      "date": "Sun, 19 Apr 2026",
      "thumbnail": "",
      "videoId": "",
      "priority": 5,
      "scoreDetail": {
        "daily": 0,
        "phil": 5,
        "flaneur": 0,
        "novelty": 0,
        "total": 5
      }
    },
    {
      "title": "Après la mort de Habermas, une longue guerre d’héritage en vue",
      "url": "https://www.philomag.com/articles/apres-la-mort-de-habermas-une-longue-guerre-dheritage-en-vue",
      "description": "",
      "date": "Sun, 19 Apr 2026",
      "thumbnail": "",
      "videoId": "",
      "priority": 5,
      "scoreDetail": {
        "daily": 5,
        "phil": 0,
        "flaneur": 0,
        "novelty": 0,
        "total": 5
      }
    },
    {
      "title": "À Gaza et au Liban, les ravages du nécropouvoir",
      "url": "https://www.philomag.com/articles/gaza-et-au-liban-les-ravages-du-necropouvoir",
      "description": "",
      "date": "Tue, 21 Apr 2026",
      "thumbnail": "",
      "videoId": "",
      "priority": 0,
      "scoreDetail": {
        "daily": 0,
        "phil": 0,
        "flaneur": 0,
        "novelty": 0,
        "total": 0
      }
    },
    {
      "title": "Pascal Bruckner : “Sans la diversité de ses auteurs, Grasset ne survivra pas”",
      "url": "https://www.philomag.com/articles/pascal-bruckner-sans-la-diversite-de-ses-auteurs-grasset-ne-survivra-pas",
      "description": "",
      "date": "Tue, 21 Apr 2026",
      "thumbnail": "",
      "videoId": "",
      "priority": 0,
      "scoreDetail": {
        "daily": 0,
        "phil": 0,
        "flaneur": 0,
        "novelty": 0,
        "total": 0
      }
    },
    {
      "title": "“Discorde”, “controverse”, “clash”… Avez-vous les mots pour décrire la dispute ?",
      "url": "https://www.philomag.com/articles/discorde-controverse-clash-avez-vous-les-mots-pour-decrire-la-dispute",
      "description": "",
      "date": "Tue, 21 Apr 2026",
      "thumbnail": "",
      "videoId": "",
      "priority": 0,
      "scoreDetail": {
        "daily": 0,
        "phil": 0,
        "flaneur": 0,
        "novelty": 0,
        "total": 0
      }
    },
    {
      "title": "“Je suis partout” : édition du dimanche",
      "url": "https://www.philomag.com/articles/je-suis-partout-edition-du-dimanche",
      "description": "",
      "date": "Mon, 20 Apr 2026",
      "thumbnail": "",
      "videoId": "",
      "priority": 0,
      "scoreDetail": {
        "daily": 0,
        "phil": 0,
        "flaneur": 0,
        "novelty": 0,
        "total": 0
      }
    },
    {
      "title": "Olivier Hamant : \"La crise énergétique actuelle est le signe typique d’un monde qui craque\"",
      "url": "https://www.philomag.com/articles/olivier-hamant-la-crise-energetique-actuelle-est-le-signe-typique-dun-monde-qui-craque",
      "description": "",
      "date": "Mon, 20 Apr 2026",
      "thumbnail": "",
      "videoId": "",
      "priority": 0,
      "scoreDetail": {
        "daily": 0,
        "phil": 0,
        "flaneur": 0,
        "novelty": 0,
        "total": 0
      }
    },
    {
      "title": "Trump contre le pape Léon XIV : les clés d’une controverse",
      "url": "https://www.philomag.com/articles/trump-contre-le-pape-leon-xiv-les-cles-dune-controverse",
      "description": "",
      "date": "Mon, 20 Apr 2026",
      "thumbnail": "",
      "videoId": "",
      "priority": 0,
      "scoreDetail": {
        "daily": 0,
        "phil": 0,
        "flaneur": 0,
        "novelty": 0,
        "total": 0
      }
    },
    {
      "title": "“J’en fais toute une histoire” : le rire stoïcien de l'écrivaine et cinéaste Nora Ephron",
      "url": "https://www.philomag.com/articles/jen-fais-toute-une-histoire-le-rire-stoicien-de-lecrivaine-et-cineaste-nora-ephron",
      "description": "",
      "date": "Mon, 20 Apr 2026",
      "thumbnail": "",
      "videoId": "",
      "priority": 0,
      "scoreDetail": {
        "daily": 0,
        "phil": 0,
        "flaneur": 0,
        "novelty": 0,
        "total": 0
      }
    }
  ]
}